Metadata-Version: 1.1
Name: fastq-anonymous
Version: 1.0.1
Summary: Change the sequence of a fastq file to enable sharing of confidential information, for troubleshooting￼ of tools.
Home-page: https://github.com/wdecoster/fastq-anonymous
Author: Wouter De Coster
Author-email: decosterwouter@gmail.com
License: MIT
Keywords: nanopore sequencing plotting quality control
Platform: UNKNOWN
Classifier: Development Status :: 4 - Beta
Classifier: Intended Audience :: Science/Research
Classifier: Topic :: Scientific/Engineering :: Bio-Informatics
Classifier: License :: OSI Approved :: MIT License
Classifier: Programming Language :: Python :: 3
Classifier: Programming Language :: Python :: 3.3
Classifier: Programming Language :: Python :: 3.4
Classifier: Programming Language :: Python :: 3.5
